pylab.py
matplotlib/animation.py
matplotlib/animation.pyi
matplotlib/artist.py
matplotlib/artist.pyi
matplotlib/axis.py
matplotlib/axis.pyi
matplotlib/backend_bases.py
matplotlib/backend_bases.pyi
matplotlib/backend_managers.py
matplotlib/backend_managers.pyi
matplotlib/backend_tools.py
matplotlib/backend_tools.pyi
matplotlib/bezier.py
matplotlib/bezier.pyi
matplotlib/category.py
matplotlib/cbook.py
matplotlib/cbook.pyi
matplotlib/cm.py
matplotlib/cm.pyi
matplotlib/collections.py
matplotlib/collections.pyi
matplotlib/colorbar.py
matplotlib/colorbar.pyi
matplotlib/colors.py
matplotlib/colors.pyi
matplotlib/container.py
matplotlib/container.pyi
matplotlib/contour.py
matplotlib/contour.pyi
matplotlib/dates.py
matplotlib/dviread.py
matplotlib/dviread.pyi
matplotlib/figure.py
matplotlib/figure.pyi
matplotlib/font_manager.py
matplotlib/font_manager.pyi
matplotlib/ft2font.cp312-win_amd64.pyd
matplotlib/ft2font.pyi
matplotlib/gridspec.py
matplotlib/gridspec.pyi
matplotlib/hatch.py
matplotlib/hatch.pyi
matplotlib/image.py
matplotlib/image.pyi
matplotlib/layout_engine.py
matplotlib/layout_engine.pyi
matplotlib/legend.py
matplotlib/legend.pyi
matplotlib/legend_handler.py
matplotlib/legend_handler.pyi
matplotlib/lines.py
matplotlib/lines.pyi
matplotlib/markers.py
matplotlib/markers.pyi
matplotlib/mathtext.py
matplotlib/mathtext.pyi
matplotlib/mlab.py
matplotlib/mlab.pyi
matplotlib/offsetbox.py
matplotlib/offsetbox.pyi
matplotlib/patches.py
matplotlib/patches.pyi
matplotlib/path.py
matplotlib/path.pyi
matplotlib/patheffects.py
matplotlib/patheffects.pyi
matplotlib/py.typed
matplotlib/pylab.py
matplotlib/pyplot.py
matplotlib/quiver.py
matplotlib/quiver.pyi
matplotlib/rcsetup.py
matplotlib/rcsetup.pyi
matplotlib/sankey.py
matplotlib/sankey.pyi
matplotlib/scale.py
matplotlib/scale.pyi
matplotlib/spines.py
matplotlib/spines.pyi
matplotlib/stackplot.py
matplotlib/stackplot.pyi
matplotlib/streamplot.py
matplotlib/streamplot.pyi
matplotlib/table.py
matplotlib/table.pyi
matplotlib-3.8.3.dist-info/DELVEWHEEL
matplotlib-3.8.3.dist-info/LICENSE
matplotlib-3.8.3.dist-info/LICENSE_AMSFONTS
matplotlib-3.8.3.dist-info/LICENSE_BAKOMA
matplotlib-3.8.3.dist-info/LICENSE_CARLOGO
matplotlib-3.8.3.dist-info/LICENSE_COLORBREWER
matplotlib-3.8.3.dist-info/LICENSE_COURIERTEN
matplotlib-3.8.3.dist-info/LICENSE_JSXTOOLS_RESIZE_OBSERVER
matplotlib-3.8.3.dist-info/LICENSE_QHULL
matplotlib-3.8.3.dist-info/LICENSE_QT4_EDITOR
matplotlib-3.8.3.dist-info/LICENSE_SOLARIZED
matplotlib-3.8.3.dist-info/LICENSE_STIX
matplotlib-3.8.3.dist-info/LICENSE_YORICK
matplotlib-3.8.3.dist-info/METADATA
matplotlib-3.8.3.dist-info/RECORD
matplotlib-3.8.3.dist-info/top_level.txt
matplotlib-3.8.3.dist-info/WHEEL
